phs_poly-0.2.3.dist-info/METADATA
phs_poly-0.2.3.dist-info/WHEEL
phs_poly.cpython-39-darwin.so
phs_poly-0.2.3.dist-info/RECORD
