Metadata-Version: 2.1
Name: phs_poly
Version: 0.2.3
Summary: PHS+poly approximation procedures
Keywords: approximation,RBF-FD,meshfree
Author-Email: Ivan Pribec <ivan.pribec@gmail.com>
License: MIT
Classifier: Development Status :: 1 - Planning
Classifier: Intended Audience :: Science/Research
Classifier: Operating System :: MacOS
Classifier: Topic :: Scientific/Engineering
Classifier: Topic :: Scientific/Engineering :: Mathematics
Classifier: Programming Language :: Fortran
Classifier: Programming Language :: Python :: 3.9
Requires-Python: >=3.9
Requires-Dist: numpy
